{
  "metups": [
    {
      "lat": 39.902599,
      "lon": -83.997257,
      "date": "4/4/2019",
      "title": "test meetup1"
    },
    {
      "lat": 39.913107,
      "lon": -84.032652,
      "date": "4/09/2019",
      "title": "test meetup2"
    },
    {
      "lat": 39.826679,
      "lon": -84.013431,
      "date": "4/15/2019",
      "title": "test meetup3"
    },
    {
      "lat": 39.833006,
      "lon": -83.961260,
      "date": "4/20/2019",
      "title": "test meetup4"
    }
  ]
}